fixer_currency/__about__.py
fixer_currency/__init__.py
fixer_currency/client.py
fixer_currency/exceptions.py
fixer_currency-0.1.0.dist-info/METADATA
fixer_currency-0.1.0.dist-info/WHEEL
fixer_currency-0.1.0.dist-info/licenses/LICENSE.txt
fixer_currency-0.1.0.dist-info/RECORD
