Metadata-Version: 2.1
Name: fixer-currency
Version: 0.1.0
Summary: A Python client for Fixer API - a currency conversion API
Project-URL: Documentation, https://github.com/jfrid/fixer-currency#readme
Project-URL: Issues, https://github.com/jfrid/fixer-currency/issues
Project-URL: Source, https://github.com/jfrid/fixer-currency
Author-email: Jonas Hårdén <1254179+jfrid@users.noreply.github.com>, Adrian Matellanes <matellanesadrian@gmail.com>
License-Expression: MIT
License-File: LICENSE.txt
Classifier: Development Status :: 4 - Beta
Classifier: Programming Language :: Python
Classifier: Programming Language :: Python :: 3.7
Classifier: Programming Language :: Python :: 3.8
Classifier: Programming Language :: Python :: 3.9
Classifier: Programming Language :: Python :: 3.10
Classifier: Programming Language :: Python :: 3.11
Classifier: Programming Language :: Python :: Implementation :: CPython
Classifier: Programming Language :: Python :: Implementation :: PyPy
Requires-Python: >=3.7
Requires-Dist: requests
